git_repo_toolkit/__init__.py
git_repo_toolkit/main.py
git_repo_toolkit-0.0.1.dist-info/LICENSE
git_repo_toolkit-0.0.1.dist-info/METADATA
git_repo_toolkit-0.0.1.dist-info/WHEEL
git_repo_toolkit-0.0.1.dist-info/top_level.txt
git_repo_toolkit-0.0.1.dist-info/RECORD
