Metadata-Version: 2.1
Name: git-repo-toolkit
Version: 0.0.1
Summary: git-repo-toolkit is your all-in-one solution for optimizing GitHub workflows
Home-page: https://github.com/farhan/git-repo-toolkit
Author: Farhan
Author-email: mfarhan133@gmail.com
Classifier: Programming Language :: Python :: 3
Classifier: Programming Language :: Python :: 3.11
Classifier: Programming Language :: Python :: 3.12
License-File: LICENSE
